Metadata-Version: 1.1
Name: static3
Version: 0.5
Summary: A really simple WSGI way to serve static (or mixed) content.
Home-page: https://github.com/rmohr/static3
Author: Roman Mohr
Author-email: roman@fenkhuber.at
License: LGPL
Keywords: wsgi web http static content webapps
Platform: UNKNOWN
Classifier: Development Status :: 4 - Beta
Classifier: Environment :: Web Environment
Classifier: Intended Audience :: Developers
Classifier: License :: OSI Approved :: GNU Library or Lesser General Public License (LGPL)
Classifier: Natural Language :: English
Classifier: Operating System :: OS Independent
Classifier: Programming Language :: Python
Classifier: Topic :: Software Development :: Libraries
Classifier: Topic :: Utilities
